scrapezone_client/__init__.py
scrapezone_client/client.py
scrapezone_python_sdk-1.0.5.dist-info/METADATA
scrapezone_python_sdk-1.0.5.dist-info/WHEEL
scrapezone_python_sdk-1.0.5.dist-info/top_level.txt
scrapezone_python_sdk-1.0.5.dist-info/RECORD
