Metadata-Version: 2.1
Name: scrapezone-python-sdk
Version: 1.0.5
Summary: Official client SDK of Scrapezone
Home-page: https://github.com/Scrapezone/scrapezone-python-sdk
Author: Scrapezone
Author-email: admin@scrapezone.com
License: MIT
Platform: UNKNOWN
Classifier: License :: OSI Approved :: MIT License
Classifier: Programming Language :: Python :: 3
Classifier: Programming Language :: Python :: 3.9
Requires-Dist: python-decouple
